odoo/addons/purchase_order_approval_block/README.rst
odoo/addons/purchase_order_approval_block/__init__.py
odoo/addons/purchase_order_approval_block/__manifest__.py
odoo/addons/purchase_order_approval_block/data/purchase_exception_data.xml
odoo/addons/purchase_order_approval_block/i18n/fr.po
odoo/addons/purchase_order_approval_block/i18n/purchase_order_approval_block.pot
odoo/addons/purchase_order_approval_block/models/__init__.py
odoo/addons/purchase_order_approval_block/models/purchase_approval_block_reason.py
odoo/addons/purchase_order_approval_block/models/purchase_order.py
odoo/addons/purchase_order_approval_block/security/ir.model.access.csv
odoo/addons/purchase_order_approval_block/security/purchase_order_approval_block_security.xml
odoo/addons/purchase_order_approval_block/static/description/icon.png
odoo/addons/purchase_order_approval_block/tests/__init__.py
odoo/addons/purchase_order_approval_block/tests/test_po_approval_block_reason.py
odoo/addons/purchase_order_approval_block/tests/test_purchase_order_approval_block.py
odoo/addons/purchase_order_approval_block/views/purchase_approval_block_reason_view.xml
odoo/addons/purchase_order_approval_block/views/purchase_order_view.xml
odoo/addons/purchase_order_approval_block/wizard/__init__.py
odoo/addons/purchase_order_approval_block/wizard/purchase_exception_confirm.py
odoo12_addon_purchase_order_approval_block-12.0.1.0.1.dist-info/METADATA
odoo12_addon_purchase_order_approval_block-12.0.1.0.1.dist-info/WHEEL
odoo12_addon_purchase_order_approval_block-12.0.1.0.1.dist-info/top_level.txt
odoo12_addon_purchase_order_approval_block-12.0.1.0.1.dist-info/RECORD
